pygetimportables-0.3.0.dist-info/METADATA
pygetimportables-0.3.0.dist-info/WHEEL
pygetimportables-0.3.0.dist-info/licenses/LICENSE
pygetimportables/__init__.py
pygetimportables/py.typed
pygetimportables-0.3.0.dist-info/RECORD
