Metadata-Version: 2.1
Name: pygetimportables
Version: 0.3.0
Summary: Python functions to get top-level importable names
Author-Email: =?utf-8?q?Juan_Luis_Cano_Rodr=C3=ADguez?= <hello@juanlu.space>
License: Copyright (c) 2023 by Juan Luis Cano Rodríguez <hello@juanlu.space>
Classifier: Development Status :: 3 - Alpha
Classifier: Intended Audience :: Developers
Classifier: License :: OSI Approved :: MIT License
Classifier: Operating System :: OS Independent
Classifier: Programming Language :: Python
Classifier: Programming Language :: Python :: 3
Classifier: Programming Language :: Python :: 3.9
Classifier: Programming Language :: Python :: 3.10
Classifier: Programming Language :: Python :: 3.11
Classifier: Programming Language :: Python :: 3.12
Project-URL: Source, https://github.com/astrojuanlu/pygetimportables
Project-URL: Tracker, https://github.com/astrojuanlu/pygetimportables/issues
Project-URL: Documentation, https://pygetimportables.readthedocs.io
Requires-Python: >=3.9
Requires-Dist: build[uv]>=1.2.0
Requires-Dist: installer
Requires-Dist: pyproject_hooks
Requires-Dist: tomli; python_version < "3.11"
Requires-Dist: validate-pyproject
Requires-Dist: mypy; extra == "test"
Requires-Dist: hypothesis; extra == "test"
Requires-Dist: pytest; extra == "test"
Requires-Dist: pytest-cov; extra == "test"
Requires-Dist: furo; extra == "doc"
Requires-Dist: myst-parser; extra == "doc"
Requires-Dist: sphinx>=5; extra == "doc"
Requires-Dist: sphinx-copybutton; extra == "doc"
Provides-Extra: test
Provides-Extra: doc
